neurodatapub/__init__.py
neurodatapub/info.py
neurodatapub/parser.py
neurodatapub/project.py
neurodatapub/cli/__init__.py
neurodatapub/cli/neurodatapub.py
neurodatapub/resources/__init__.py
neurodatapub/resources/neurodatapub_logo_100x100.png
neurodatapub/resources/save_json_icon_50x50.png
neurodatapub/resources/save_json_icon_50x50_pressed.png
neurodatapub/resources/synapsy_logo.png
neurodatapub/ui/__init__.py
neurodatapub/ui/project.py
neurodatapub/utils/__init__.py
neurodatapub/utils/datalad.py
neurodatapub/utils/gitannex.py
neurodatapub/utils/github.py
neurodatapub/utils/io.py
neurodatapub/utils/jsonconfig.py
neurodatapub/utils/process.py
neurodatapub/utils/qt.py
neurodatapub/utils/sshconfig.py
neurodatapub-0.4.dist-info/LICENSE
neurodatapub-0.4.dist-info/METADATA
neurodatapub-0.4.dist-info/WHEEL
neurodatapub-0.4.dist-info/entry_points.txt
neurodatapub-0.4.dist-info/top_level.txt
neurodatapub-0.4.dist-info/RECORD
