Metadata-Version: 2.1
Name: neurodatapub
Version: 0.4
Summary: NeuroDataPub: Tool built for publication of BIDS datasets of the NCCR-Synapsy
Home-page: https://github.com/NCCR-SYNAPSY/neurodatapub
Author: Sebastien Tourbier
Author-email: sebastien.tourbier@alumni.epfl.ch
Maintainer: Connectomics lab, University Hospital of Lausanne and the NeuroDataPub developers
Maintainer-email: sebastien.tourbier@alumni.epfl.ch
License: Apache-2.0
Platform: UNKNOWN
Classifier: Development Status :: 4 - Beta
Classifier: Intended Audience :: Science/Research
Classifier: Intended Audience :: Developers
Classifier: License :: OSI Approved
Classifier: Programming Language :: Python
Classifier: Topic :: Software Development
Classifier: Topic :: Scientific/Engineering
Classifier: Operating System :: Microsoft :: Windows
Classifier: Operating System :: POSIX
Classifier: Operating System :: Unix
Classifier: Operating System :: MacOS
Classifier: Programming Language :: Python :: 3.8
Requires-Python: >=3.8
License-File: LICENSE
